papersync/__init__.py
papersync/cli.py
papersync/utils.py
papersync/data/__init__.py
papersync/data/papersync.yaml
papersync-0.1.0.dist-info/LICENSE
papersync-0.1.0.dist-info/METADATA
papersync-0.1.0.dist-info/WHEEL
papersync-0.1.0.dist-info/entry_points.txt
papersync-0.1.0.dist-info/top_level.txt
papersync-0.1.0.dist-info/RECORD
