Metadata-Version: 2.1
Name: papersync
Version: 0.1.0
Summary: A tool for syncing LaTeX projects with Git and external folders.
Home-page: https://github.com/rferrali/papersync
Author: Romain Ferrali
Author-email: Romain Ferrali <rferrali@gmail.com>
License: GPL3
Project-URL: Homepage, https://github.com/rferrali/papersync
Keywords: latex,git,sync
Classifier: Programming Language :: Python :: 3
Classifier: Operating System :: OS Independent
Requires-Python: >=3.8
License-File: LICENSE
Requires-Dist: click>=8.1
Requires-Dist: GitPython>=3.1
Requires-Dist: python-dotenv>=1.0
Requires-Dist: pyyaml>=5.3
